my_math_operations_gdprall/__init__.py
my_math_operations_gdprall/test_my_math_operations_gdprall.py
my_math_operations_gdprall-0.0.1.dist-info/METADATA
my_math_operations_gdprall-0.0.1.dist-info/WHEEL
my_math_operations_gdprall-0.0.1.dist-info/licenses/LICENSE
my_math_operations_gdprall-0.0.1.dist-info/RECORD
