Metadata-Version: 2.1
Name: my_math_operations_gdprall
Version: 0.0.1
Summary: A small example package with some math operations
Author-email: Gibson Prall <gdprall@sandia.gov>
License-File: LICENSE
Classifier: License :: OSI Approved :: MIT License
Classifier: Operating System :: OS Independent
Classifier: Programming Language :: Python :: 3
Requires-Python: >=3.7
